mpi_cbs/mediforms/__init__.py
mpi_cbs/mediforms/admin.py
mpi_cbs/mediforms/apps.py
mpi_cbs/mediforms/forms.py
mpi_cbs/mediforms/models.py
mpi_cbs/mediforms/urls.py
mpi_cbs/mediforms/views.py
mpi_cbs/mediforms/widgets.py
mpi_cbs/mediforms/locale/de/LC_MESSAGES/django.mo
mpi_cbs/mediforms/locale/de/LC_MESSAGES/django.po
mpi_cbs/mediforms/locale/en/LC_MESSAGES/django.mo
mpi_cbs/mediforms/locale/en/LC_MESSAGES/django.po
mpi_cbs/mediforms/management/__init__.py
mpi_cbs/mediforms/management/commands/__init__.py
mpi_cbs/mediforms/management/commands/process_pdf_rendering_jobs.py
mpi_cbs/mediforms/migrations/0001_initial.py
mpi_cbs/mediforms/migrations/0002_alter_formdatamrt_email_alter_formdatamrt7tptx_email_and_more.py
mpi_cbs/mediforms/migrations/0003_remove_formdatamrtconnectom_token_created_by_and_more.py
mpi_cbs/mediforms/migrations/0004_pdfrenderingjob.py
mpi_cbs/mediforms/migrations/__init__.py
mpi_cbs/mediforms/templates/mediforms/base.html
mpi_cbs/mediforms/templates/mediforms/index.html
mpi_cbs/mediforms/templates/mediforms/login.html
mpi_cbs/mediforms/templates/mediforms/success.html
mpi_cbs/mediforms/templates/mediforms/token_list.html
mpi_cbs/mediforms/templates/mediforms/emails/base.txt
mpi_cbs/mediforms/templates/mediforms/emails/mrt.txt
mpi_cbs/mediforms/templates/mediforms/emails/mrtbegleitung.txt
mpi_cbs/mediforms/templates/mediforms/emails/tms.txt
mpi_cbs/mediforms/templates/mediforms/includes/.information_text_mrt.html.swp
mpi_cbs/mediforms/templates/mediforms/includes/data_protection_declaration_mrt.html
mpi_cbs/mediforms/templates/mediforms/includes/data_protection_declaration_tms.html
mpi_cbs/mediforms/templates/mediforms/includes/data_storage_and_usage_consent_mrtbegleitung.html
mpi_cbs/mediforms/templates/mediforms/includes/exploration_consent_mrt.html
mpi_cbs/mediforms/templates/mediforms/includes/exploration_consent_mrtbegleitung.html
mpi_cbs/mediforms/templates/mediforms/includes/exploration_consent_tms.html
mpi_cbs.mediforms-0.3.1rc30.dist-info/METADATA
mpi_cbs.mediforms-0.3.1rc30.dist-info/WHEEL
mpi_cbs.mediforms-0.3.1rc30.dist-info/top_level.txt
mpi_cbs.mediforms-0.3.1rc30.dist-info/RECORD
